{
  "format": "custom",
  "id": "blog_post",
  "label": "Blog Post",
  "repeatable": true,
  "status": true,
  "json": {
    "Main": {
      "uid": {
        "type": "UID",
        "config": {
          "label": "UID"
        }
      },
      "category": {
        "type": "Text",
        "config": {
          "label": "Category",
          "placeholder": ""
        }
      },
      "featured_image": {
        "type": "Image",
        "config": {
          "label": "Featured Image",
          "constraint": {},
          "thumbnails": []
        }
      },
      "title": {
        "type": "StructuredText",
        "config": {
          "label": "Title",
          "placeholder": "",
          "allowTargetBlank": true,
          "multi": "paragraph,preformatted,heading1,heading2,heading3,heading4,heading5,heading6,strong,em,hyperlink,image,embed,list-item,o-list-item,rtl"
        }
      },
      "sub_title": {
        "type": "StructuredText",
        "config": {
          "label": "Sub Title",
          "placeholder": "",
          "allowTargetBlank": true,
          "multi": "paragraph,preformatted,heading1,heading2,heading3,heading4,heading5,heading6,strong,em,hyperlink,image,embed,list-item,o-list-item,rtl"
        }
      },
      "content": {
        "type": "StructuredText",
        "config": {
          "label": "Content",
          "placeholder": "",
          "allowTargetBlank": true,
          "multi": "paragraph,preformatted,heading1,heading2,heading3,heading4,heading5,heading6,strong,em,hyperlink,image,embed,list-item,o-list-item,rtl"
        }
      },
      "publish_date": {
        "type": "Date",
        "config": {
          "label": "Publish Date",
          "placeholder": ""
        }
      },
      "shareable_links": {
        "type": "Link",
        "config": {
          "label": "Shareable Links",
          "placeholder": "",
          "select": null,
          "allowTargetBlank": true,
          "allowText": true,
          "repeat": true
        }
      }
    }
  }
}
